rvc/__init__.py
rvc/configs/config.py
rvc/configs/v1/32k.json
rvc/configs/v1/40k.json
rvc/configs/v1/48k.json
rvc/configs/v2/32k.json
rvc/configs/v2/48k.json
rvc/lib/audio.py
rvc/lib/infer_pack/attentions.py
rvc/lib/infer_pack/commons.py
rvc/lib/infer_pack/models.py
rvc/lib/infer_pack/models_onnx.py
rvc/lib/infer_pack/modules/F0Predictor/DioF0Predictor.py
rvc/lib/infer_pack/modules/F0Predictor/F0Predictor.py
rvc/lib/infer_pack/modules/F0Predictor/HarvestF0Predictor.py
rvc/lib/infer_pack/modules/F0Predictor/PMF0Predictor.py
rvc/lib/infer_pack/modules/F0Predictor/__init__.py
rvc/lib/infer_pack/modules.py
rvc/lib/infer_pack/onnx_inference.py
rvc/lib/infer_pack/transforms.py
rvc/lib/ipex/__init__.py
rvc/lib/ipex/attention.py
rvc/lib/ipex/gradscaler.py
rvc/lib/ipex/hijacks.py
rvc/lib/jit/__init__.py
rvc/lib/jit/get_hubert.py
rvc/lib/jit/get_rmvpe.py
rvc/lib/jit/get_synthesizer.py
rvc/lib/rmvpe.py
rvc/lib/slicer2.py
rvc/lib/train/architecture/v1.yml
rvc/lib/train/architecture/v2.yml
rvc/lib/train/data_utils.py
rvc/lib/train/losses.py
rvc/lib/train/mel_processing.py
rvc/lib/train/process_ckpt.py
rvc/lib/train/utils.py
rvc/lib/uvr5_pack/lib_v5/dataset.py
rvc/lib/uvr5_pack/lib_v5/layers.py
rvc/lib/uvr5_pack/lib_v5/layers_123812KB .py
rvc/lib/uvr5_pack/lib_v5/layers_123821KB.py
rvc/lib/uvr5_pack/lib_v5/layers_33966KB.py
rvc/lib/uvr5_pack/lib_v5/layers_537227KB.py
rvc/lib/uvr5_pack/lib_v5/layers_537238KB.py
rvc/lib/uvr5_pack/lib_v5/layers_new.py
rvc/lib/uvr5_pack/lib_v5/model_param_init.py
rvc/lib/uvr5_pack/lib_v5/modelparams/1band_sr16000_hl512.json
rvc/lib/uvr5_pack/lib_v5/modelparams/1band_sr32000_hl512.json
rvc/lib/uvr5_pack/lib_v5/modelparams/1band_sr33075_hl384.json
rvc/lib/uvr5_pack/lib_v5/modelparams/1band_sr44100_hl1024.json
rvc/lib/uvr5_pack/lib_v5/modelparams/1band_sr44100_hl256.json
rvc/lib/uvr5_pack/lib_v5/modelparams/1band_sr44100_hl512.json
rvc/lib/uvr5_pack/lib_v5/modelparams/1band_sr44100_hl512_cut.json
rvc/lib/uvr5_pack/lib_v5/modelparams/2band_32000.json
rvc-0.3.5.dist-info/LICENSE
rvc-0.3.5.dist-info/METADATA
rvc-0.3.5.dist-info/WHEEL
rvc-0.3.5.dist-info/entry_points.txt
rvc-0.3.5.dist-info/RECORD
