Metadata-Version: 2.1
Name: rvc
Version: 0.3.5
Summary: An easy-to-use Voice Conversion framework based on VITS.
Author: Ftps
Author-email: ftpsflandre@gmail.com
Requires-Python: >=3.10,<4.0
Classifier: Programming Language :: Python :: 3
Classifier: Programming Language :: Python :: 3.10
Classifier: Programming Language :: Python :: 3.11
Classifier: Programming Language :: Python :: 3.12
Provides-Extra: api
Requires-Dist: av (>=11.0.0,<12.0.0)
Requires-Dist: click (>=8.1.7,<9.0.0)
Requires-Dist: fairseq (>=0.12.2,<0.13.0)
Requires-Dist: faiss-cpu (>=1.7.4,<2.0.0)
Requires-Dist: fastapi (>=0.109.0,<0.110.0) ; extra == "api"
Requires-Dist: librosa (>=0.10.1,<0.11.0)
Requires-Dist: numba (==0.59.0rc1)
Requires-Dist: poethepoet (>=0.24.4,<0.25.0)
Requires-Dist: praat-parselmouth (>=0.4.3,<0.5.0)
Requires-Dist: pydub (>=0.25.1,<0.26.0)
Requires-Dist: python-dotenv (>=1.0.0,<2.0.0)
Requires-Dist: python-multipart (>=0.0.6,<0.0.7)
Requires-Dist: pyworld (>=0.3.4,<0.4.0)
Requires-Dist: soundfile (>=0.12.1,<0.13.0)
Requires-Dist: tensorboardx (>=2.6.2.2,<3.0.0.0)
Requires-Dist: torch (>=2.1.0,<3.0.0)
Requires-Dist: torchcrepe (>=0.0.22,<0.0.23)
Requires-Dist: uvicorn (>=0.26.0,<0.27.0) ; extra == "api"
Project-URL: github, https://github.com/RVC-Project/Retrieval-based-Voice-Conversion
